{
"type": "FeatureCollection",
"name": "State Institute of Health and Family Welfare",
"crs": { "type": "name", "properties": { "name": "urn:ogc:def:crs:OGC:1.3:CRS84" } },
"features": [
{ "type": "Feature", "properties": { "OBJECTID": 1, "DepartmentCode": "111", "KGISCode": "29572055428031620000HFHFWINTCRSIH0001", "KGISSHWID": 1, "SHWName": "State Institute of Health and Family Welfare, Bangalore", "KGISVillageID": 15109, "KGISWardID": 0 }, "geometry": { "type": "Point", "coordinates": [ 77.565092149835479, 12.973116254310156 ] } }
]
}
