{
"type": "FeatureCollection",
"name": "Ayush Research Centre",
"crs": { "type": "name", "properties": { "name": "urn:ogc:def:crs:OGC:1.3:CRS84" } },
"features": [
{ "type": "Feature", "properties": { "OBJECTID": 28, "DepartmentCode": "1", "KGISVillageID": 28458, "KGISWardID": null, "KGISCode": "29577055728031940000HFAYUDURCCARC0001", "AyushResearchCentreName": "Ayush Research Centre, Mysore", "KGISARCID": 1 }, "geometry": { "type": "Point", "coordinates": [ 76.632049926890119, 12.342049928328857 ] } }
]
}
